{
"type": "FeatureCollection",
"name": "hcd-011125",
"crs": { "type": "name", "properties": { "name": "urn:ogc:def:crs:OGC:1.3:CRS84" } },
"features": [
{ "type": "Feature", "properties": { "OBJECTID_1": 108330, "County_Name": "LOS ANGELES", "fips_apn": "06037_7054013001", "jurisdiction_name": "CERRITOS", "Site_Address_Intersection": "19318 Ely Ave", "AssessorParcelNumber": "7054-013-001", "Consolidated_Sites": "A", "General_Plan_Designation_Curren": "Low Density", "Zoning_Designation_Current": "RS-6500", "Minimum_Density_Allowed_units_p": 2.0, "Max_Density_Allowed_units_per_a": "5.5", "Parcel_Size_Acres": 0.73, "Existing_Use_Vacancy": "Residential, 1", "Infrastructure": "YES - Planned", "Publicly_Owned": "NO - Privately-Owned", "Site_Status": "Pending Project", "Identified_in_Last_Two_Planning": "Used in Two Consecutive Prior Housing Elements - Vacant", "Lower_Income_Capacity": null, "Moderate_Income_Capacity": null, "Above_Moderate_Income_Capacity": 1.0, "Total_Capacity": 1.0, "Latitude": 33.85502319, "Longitude": -118.06831088, "Zoning_Designation_Current_Desc": "Single-family dwellings. https://www.codepublishing.com/CA/Cerritos/#!/Cerritos22/Cerritos2222.html#22.22", "Zip_Code": "90703" }, "geometry": { "type": "Point", "coordinates": [ -13143304.2457, 4009351.755400000140071 ] } },
{ "type": "Feature", "properties": { "OBJECTID_1": 108331, "County_Name": "LOS ANGELES", "fips_apn": "06037_7054013002", "jurisdiction_name": "CERRITOS", "Site_Address_Intersection": "19402 Ely Ave", "AssessorParcelNumber": "7054-013-002", "Consolidated_Sites": "A", "General_Plan_Designation_Curren": "Low Density", "Zoning_Designation_Current": "RS-6500", "Minimum_Density_Allowed_units_p": 2.0, "Max_Density_Allowed_units_per_a": "5.5", "Parcel_Size_Acres": 0.48, "Existing_Use_Vacancy": "Residential, 1", "Infrastructure": "YES - Planned", "Publicly_Owned": "NO - Privately-Owned", "Site_Status": "Pending Project", "Identified_in_Last_Two_Planning": "Used in Two Consecutive Prior Housing Elements - Vacant", "Lower_Income_Capacity": null, "Moderate_Income_Capacity": null, "Above_Moderate_Income_Capacity": 1.0, "Total_Capacity": 1.0, "Latitude": 33.85480931, "Longitude": -118.06830693000001, "Zoning_Designation_Current_Desc": "Single-family dwellings. https://www.codepublishing.com/CA/Cerritos/#!/Cerritos22/Cerritos2222.html#22.22", "Zip_Code": "90703" }, "geometry": { "type": "Point", "coordinates": [ -13143303.8057, 4009323.085400000214577 ] } },
{ "type": "Feature", "properties": { "OBJECTID_1": 108332, "County_Name": "LOS ANGELES", "fips_apn": "06037_7054013003", "jurisdiction_name": "CERRITOS", "Site_Address_Intersection": "19408 Ely Ave", "AssessorParcelNumber": "7054-013-003", "Consolidated_Sites": "A", "General_Plan_Designation_Curren": "Low Density", "Zoning_Designation_Current": "RS-6500", "Minimum_Density_Allowed_units_p": 2.0, "Max_Density_Allowed_units_per_a": "5.5", "Parcel_Size_Acres": 0.44, "Existing_Use_Vacancy": "Residential, 1", "Infrastructure": "YES - Planned", "Publicly_Owned": "NO - Privately-Owned", "Site_Status": "Pending Project", "Identified_in_Last_Two_Planning": "Used in Two Consecutive Prior Housing Elements - Vacant", "Lower_Income_Capacity": null, "Moderate_Income_Capacity": null, "Above_Moderate_Income_Capacity": 1.0, "Total_Capacity": 1.0, "Latitude": 33.85464722, "Longitude": -118.06830393, "Zoning_Designation_Current_Desc": "Single-family dwellings. https://www.codepublishing.com/CA/Cerritos/#!/Cerritos22/Cerritos2222.html#22.22", "Zip_Code": "90703" }, "geometry": { "type": "Point", "coordinates": [ -13143303.4724, 4009301.3574 ] } }
]
}
