{
"type": "FeatureCollection",
"name": "hcd-011125",
"crs": { "type": "name", "properties": { "name": "urn:ogc:def:crs:OGC:1.3:CRS84" } },
"features": [
{ "type": "Feature", "properties": { "OBJECTID_1": 40664, "County_Name": "ORANGE", "fips_apn": "06059_03223229", "jurisdiction_name": "FULLERTON", "Site_Address_Intersection": "100 W AMERIGE AVE", "AssessorParcelNumber": "032-232-29", "Consolidated_Sites": null, "General_Plan_Designation_Curren": "Downtown Mixed Use", "Zoning_Designation_Current": "C-3 Central Business", "Minimum_Density_Allowed_units_p": 0.0, "Max_Density_Allowed_units_per_a": "0", "Parcel_Size_Acres": 0.98, "Existing_Use_Vacancy": "Parking", "Infrastructure": "YES - Current", "Publicly_Owned": "YES - City-Owned", "Site_Status": "Available", "Identified_in_Last_Two_Planning": "Not Used in Prior Housing Element", "Lower_Income_Capacity": 5.0, "Moderate_Income_Capacity": 0.0, "Above_Moderate_Income_Capacity": 48.0, "Total_Capacity": 53, "Latitude": 33.87166838, "Longitude": -117.92552651, "Zoning_Designation_Current_Desc": "High Density Residential/Commercial Mixed-use; https://codelibrary.amlegal.com/codes/fullerton/latest/fullerton_ca/0-0-0-30272#JD_15.30.030.3", "Zip_Code": "92832" }, "geometry": { "type": "Point", "coordinates": [ -13127409.5628, 4011583.2138 ] } },
{ "type": "Feature", "properties": { "OBJECTID_1": 40669, "County_Name": "ORANGE", "fips_apn": "06059_03223428", "jurisdiction_name": "FULLERTON", "Site_Address_Intersection": "100 W AMERIGE AVE", "AssessorParcelNumber": "032-234-28", "Consolidated_Sites": null, "General_Plan_Designation_Curren": "Downtown Mixed Use", "Zoning_Designation_Current": "C-3 Central Business", "Minimum_Density_Allowed_units_p": 0.0, "Max_Density_Allowed_units_per_a": "0", "Parcel_Size_Acres": 1.15, "Existing_Use_Vacancy": "Parking", "Infrastructure": "YES - Current", "Publicly_Owned": "YES - City-Owned", "Site_Status": "Available", "Identified_in_Last_Two_Planning": "Not Used in Prior Housing Element", "Lower_Income_Capacity": 6.0, "Moderate_Income_Capacity": 0.0, "Above_Moderate_Income_Capacity": 57.0, "Total_Capacity": 63, "Latitude": 33.87111645, "Longitude": -117.92554069000001, "Zoning_Designation_Current_Desc": "High Density Residential/Commercial Mixed-use; https://codelibrary.amlegal.com/codes/fullerton/latest/fullerton_ca/0-0-0-30272#JD_15.30.030.3", "Zip_Code": "92832" }, "geometry": { "type": "Point", "coordinates": [ -13127411.1415, 4011509.214800000190735 ] } },
{ "type": "Feature", "properties": { "OBJECTID_1": 40677, "County_Name": "ORANGE", "fips_apn": "06059_03223213", "jurisdiction_name": "FULLERTON", "Site_Address_Intersection": "141 E AMERIGE AVE", "AssessorParcelNumber": "032-232-13", "Consolidated_Sites": null, "General_Plan_Designation_Curren": "Downtown Mixed Use", "Zoning_Designation_Current": "C-3 Central Business", "Minimum_Density_Allowed_units_p": 0.0, "Max_Density_Allowed_units_per_a": "0", "Parcel_Size_Acres": 0.24, "Existing_Use_Vacancy": "Parking", "Infrastructure": "YES - Current", "Publicly_Owned": "YES - City-Owned", "Site_Status": "Available", "Identified_in_Last_Two_Planning": "Not Used in Prior Housing Element", "Lower_Income_Capacity": 1.0, "Moderate_Income_Capacity": 0.0, "Above_Moderate_Income_Capacity": 12.0, "Total_Capacity": 13, "Latitude": 33.87166229, "Longitude": -117.92615169, "Zoning_Designation_Current_Desc": "High Density Residential/Commercial Mixed-use; https://codelibrary.amlegal.com/codes/fullerton/latest/fullerton_ca/0-0-0-30272#JD_15.30.030.3", "Zip_Code": "92832" }, "geometry": { "type": "Point", "coordinates": [ -13127479.1578, 4011582.3972 ] } }
]
}
